PyBitTorrent/Bittorrent.py
PyBitTorrent/Block.py
PyBitTorrent/Exceptions.py
PyBitTorrent/HTTPTracker.py
PyBitTorrent/Message.py
PyBitTorrent/MessageFactory.py
PyBitTorrent/Peer.py
PyBitTorrent/PeersManager.py
PyBitTorrent/Piece.py
PyBitTorrent/PiecesManager.py
PyBitTorrent/TorrentFile.py
PyBitTorrent/Tracker.py
PyBitTorrent/TrackerFactory.py
PyBitTorrent/TrackerManager.py
PyBitTorrent/UDPTracker.py
PyBitTorrent/UDPTrackerMessage.py
PyBitTorrent/Utils.py
PyBitTorrent/__init__.py
PyBitTorrent-0.5.6.dist-info/LICENCE
PyBitTorrent-0.5.6.dist-info/METADATA
PyBitTorrent-0.5.6.dist-info/WHEEL
PyBitTorrent-0.5.6.dist-info/top_level.txt
PyBitTorrent-0.5.6.dist-info/RECORD
