Metadata-Version: 2.1
Name: PyBitTorrent
Version: 0.5.6
Summary: Download torrent files according to BitTorrent specifications
Home-page: https://github.com/gaffner/PyBitTorrent
Author: Gaffner
Author-email: gefen102@gmail.com
License: LICENSE.txt
Classifier: Programming Language :: Python :: 3.9
Classifier: Programming Language :: Python :: 3.8
Classifier: License :: OSI Approved :: MIT License
Classifier: Operating System :: OS Independent
License-File: LICENCE
Requires-Dist: bcoding (~=1.5)
Requires-Dist: bitstring (~=4.0.1)
Requires-Dist: rich (~=12.6.0)
Requires-Dist: requests (~=2.22.0)
